LICENSE
MANIFEST.in
README
setup.py
webpy_celery/__init__.py
webpy_celery/webpy_celery.py
webpy_celery.egg-info/PKG-INFO
webpy_celery.egg-info/SOURCES.txt
webpy_celery.egg-info/dependency_links.txt
webpy_celery.egg-info/not-zip-safe
webpy_celery.egg-info/requires.txt
webpy_celery.egg-info/top_level.txt